hifigan_vocoder/__init__.py
hifigan_vocoder/env.py
hifigan_vocoder/inference.py
hifigan_vocoder/inference_e2e.py
hifigan_vocoder/meldataset.py
hifigan_vocoder/models.py
hifigan_vocoder/sample_mel.pt
hifigan_vocoder/train.py
hifigan_vocoder/utils.py
hifigan_vocoder-0.1.1.dist-info/LICENSE
hifigan_vocoder-0.1.1.dist-info/METADATA
hifigan_vocoder-0.1.1.dist-info/WHEEL
hifigan_vocoder-0.1.1.dist-info/top_level.txt
hifigan_vocoder-0.1.1.dist-info/RECORD
