Metadata-Version: 2.1
Name: hifigan-vocoder
Version: 0.1.1
Summary: A wrapped hifi-gan vocoder for easy use.
Home-page: https://github.com/mushanshanshan/hifigan
Author: Mushan
License: MIT
Keywords: None
Platform: UNKNOWN
Classifier: Environment :: Console
Classifier: License :: OSI Approved :: MIT License
Classifier: Programming Language :: Python :: 3.7
License-File: LICENSE
Requires-Dist: numpy
Requires-Dist: torch
Requires-Dist: gdown
